orch_serv/__init__.py
orch_serv/exc.py
orch_serv/settings.py
orch_serv/msg/__init__.py
orch_serv/msg/message.py
orch_serv/orchestrator/__init__.py
orch_serv/orchestrator/block/__init__.py
orch_serv/orchestrator/block/async_block.py
orch_serv/orchestrator/block/base_block.py
orch_serv/orchestrator/block/sync_block.py
orch_serv/orchestrator/flow/__init__.py
orch_serv/orchestrator/flow/async_flow.py
orch_serv/orchestrator/flow/base_flow.py
orch_serv/orchestrator/flow/sync_flow.py
orch_serv/orchestrator/orchestrator/__init__.py
orch_serv/orchestrator/orchestrator/async_orchestrator.py
orch_serv/orchestrator/orchestrator/sync_orchestrator.py
orch_serv/service/__init__.py
orch_serv/service/service.py
orch_serv/stepper/__init__.py
orch_serv/stepper/stepper.py
orch_serv/stepper/utils.py
orch_serv-0.2.0.dist-info/licenses/LICENSE
orch_serv-0.2.0.dist-info/METADATA
orch_serv-0.2.0.dist-info/WHEEL
orch_serv-0.2.0.dist-info/top_level.txt
orch_serv-0.2.0.dist-info/RECORD
