Metadata-Version: 2.4
Name: orch_serv
Version: 0.2.0
Summary: Library for fast build service and interaction management
Author-email: Denis Shchutskyi <denisshchutskyi@gmail.com>
Requires-Python: >=3.10
License-File: LICENSE
Requires-Dist: pydantic>=2.10.6
Dynamic: license-file
